algos.py
app.py
db.py
db_init.py
profiler.py
transformers.py
dataforge_cli-0.2.1.dist-info/METADATA
dataforge_cli-0.2.1.dist-info/WHEEL
dataforge_cli-0.2.1.dist-info/entry_points.txt
dataforge_cli-0.2.1.dist-info/top_level.txt
dataforge_cli-0.2.1.dist-info/RECORD
