Metadata-Version: 2.4
Name: dataforge-cli
Version: 0.2.1
Summary: A CLI for reproducible data cleaning pipelines.
Author-email: Aditya <bit2swaz@gmail.com>
Project-URL: Homepage, https://github.com/bit2swaz/dataforge-python
Classifier: Programming Language :: Python :: 3
Classifier: Operating System :: OS Independent
Requires-Python: >=3.10
Requires-Dist: pandas
Requires-Dist: numpy
Requires-Dist: mysql-connector-python
Requires-Dist: python-dotenv
Requires-Dist: click
Requires-Dist: scikit-learn
Provides-Extra: dev
Requires-Dist: pytest; extra == "dev"
